{
  "name": "integration",
  "environment_variables": [],
  "group" : "example-with-infra-team-intermediate-state-with-dvts",
  "materials": [
    {
      "type": "dependency",
      "name": "dependency",
      "pipeline": "test-infra-verification",
      "stage": "test-infra-verification"
    }
  ],
  "stages": [
    {
      "name": "integration",
      "fetch_materials": true,
      "never_cleanup_artifacts": false,
      "clean_working_directory": false,
      "environment_variables": [],
      "jobs": [
        {
          "name": "integration",
          "environment_variables": [],
          "tabs": [],
          "resources": [],
          "artifacts": [],
          "properties": [],
          "run_instance_count": null,
          "timeout": 0,
          "tasks": [
            {
              "type": "exec",
              "run_if": "passed",
              "on_cancel" : null,
              "command": "ls",
              "arguments": [
                "-l",
                "."
              ],
              "working_directory": null
            }
          ]
        }
      ]
    }
  ]
}
